pubpypack_harmony_william_blackerby-0.0.3.dist-info/RECORD
pubpypack_harmony_william_blackerby-0.0.3.dist-info/LICENSE
pubpypack_harmony_william_blackerby-0.0.3.dist-info/WHEEL
pubpypack_harmony_william_blackerby-0.0.3.dist-info/entry_points.txt
pubpypack_harmony_william_blackerby-0.0.3.dist-info/top_level.txt
pubpypack_harmony_william_blackerby-0.0.3.dist-info/METADATA
imppkg/harmonic_mean.pyx
imppkg/__init__.py
imppkg/harmony.py
imppkg/data.json
imppkg/harmonic_mean.cpython-39-darwin.so
imppkg/py.typed
imppkg/harmonic_mean.c
