Metadata-Version: 2.1
Name: pubpypack-harmony-william-blackerby
Version: 0.0.3
Summary: This package does amazing things.
Home-page: https://github.com/blackerby/first-python-package
Author: William Blackerby
Author-email: "William Blackerby" <wmblackerby@gmail.com>
License: MIT
Classifier: License :: OSI Approved :: MIT License
License-File: LICENSE
Requires-Dist: termcolor <2,>=1.1.0
